django_ratelimit_backend-2.0.dist-info/METADATA
django_ratelimit_backend-2.0.dist-info/RECORD
django_ratelimit_backend-2.0.dist-info/WHEEL
django_ratelimit_backend-2.0.dist-info/top_level.txt
ratelimitbackend/__init__.py
ratelimitbackend/admin.py
ratelimitbackend/backends.py
ratelimitbackend/exceptions.py
ratelimitbackend/forms.py
ratelimitbackend/middleware.py
ratelimitbackend/models.py
ratelimitbackend/views.py
