Metadata-Version: 2.1
Name: django-ratelimit-backend
Version: 2.0
Summary: Login rate-limiting at the auth backend level
Home-page: https://github.com/brutasse/django-ratelimit-backend
Author: Bruno Renié
Author-email: bruno@renie.fr
License: BSD licence, see LICENCE file
Platform: UNKNOWN
Classifier: Development Status :: 5 - Production/Stable
Classifier: Environment :: Web Environment
Classifier: Framework :: Django
Classifier: Framework :: Django :: 1.11
Classifier: Framework :: Django :: 2.0
Classifier: Intended Audience :: Developers
Classifier: License :: OSI Approved :: BSD License
Classifier: Natural Language :: English
Classifier: Programming Language :: Python
Classifier: Programming Language :: Python :: 2.7
Classifier: Programming Language :: Python :: 3
Classifier: Programming Language :: Python :: 3.4
Classifier: Programming Language :: Python :: 3.5
Requires-Dist: Django
